epiclean/__init__.py
epiclean/clean_epigraphia.py
epiclean/cleaner.py
epiclean-0.0.5.dist-info/LICENSE
epiclean-0.0.5.dist-info/METADATA
epiclean-0.0.5.dist-info/WHEEL
epiclean-0.0.5.dist-info/top_level.txt
epiclean-0.0.5.dist-info/RECORD
