Metadata-Version: 2.1
Name: epiclean
Version: 0.0.5
Summary: A package for data cleaning inscriptions in Epigraphia Carnatica
Home-page: https://github.com/ShreyasKolpe/epigraphia-data-cleaning/tree/main/automation
Author: Shreyas Kolpe
Author-email: shreyas10.kolpe@gmail.com
Project-URL: Epigraphia REST APIs, https://github.com/ShreyasKolpe/epigraphia-rest-apis
Classifier: Programming Language :: Python :: 3
Classifier: License :: OSI Approved :: MIT License
Classifier: Operating System :: OS Independent
Requires-Python: >=3.7
License-File: LICENSE
